{"id": 4147, "keywords": [{"id": 18712, "name": "based on graphic novel"}, {"id": 174984, "name": "homework"}, {"id": 174985, "name": "shot in the chin"}, {"id": 174994, "name": "soft boiled egg"}, {"id": 175001, "name": "learning to drive"}, {"id": 175005, "name": "spoiled son"}, {"id": 175007, "name": "scarred face"}, {"id": 175008, "name": "thompson sub machine gun"}, {"id": 175011, "name": "frost on a window"}, {"id": 175016, "name": "cauterizing a wound"}, {"id": 175017, "name": "liberty half dollar"}]}