{"id": 501, "keywords": [{"id": 314, "name": "life and death"}, {"id": 1890, "name": "camping"}, {"id": 2217, "name": "rain"}, {"id": 2249, "name": "camcorder"}, {"id": 2488, "name": "self-abandonment"}, {"id": 2522, "name": "grizzly bear"}, {"id": 2524, "name": "non-governmental organisation"}, {"id": 2526, "name": "human animal relationship"}, {"id": 2527, "name": "fox"}, {"id": 5565, "name": "biography"}, {"id": 6059, "name": "unsociability"}, {"id": 6311, "name": "katmai national park"}, {"id": 9880, "name": "alaska"}, {"id": 9898, "name": "animal rights"}, {"id": 9902, "name": "wildlife"}, {"id": 15174, "name": "ecology"}]}