{"num_results": 30429, "status": "OK", "copyright": "Copyright (c) 2017 The New York Times Company.  All Rights Reserved.", "results": [{"reviews": [{"article_chapter_link": "", "book_review_link": "", "first_chapter_link": "", "sunday_review_link": ""}], "ranks_history": [{"display_name": "Espionage", "asterisk": 0, "ranks_last_week": null, "list_name": "Espionage", "weeks_on_list": 0, "published_date": "2017-01-15", "primary_isbn10": "0143130609", "dagger": 0, "bestsellers_date": "2016-12-31", "primary_isbn13": "9780143130604", "rank": 3}, {"display_name": "Espionage", "asterisk": 0, "ranks_last_week": null, "list_name": "Espionage", "weeks_on_list": 0, "published_date": "2016-12-11", "primary_isbn10": "0143130609", "dagger": 0, "bestsellers_date": "2016-11-26", "primary_isbn13": "9780143130604", "rank": 7}, {"display_name": "Espionage", "asterisk": 0, "ranks_last_week": null, "list_name": "Espionage", "weeks_on_list": 0, "published_date": "2016-11-13", "primary_isbn10": "0143130609", "dagger": 0, "bestsellers_date": "2016-10-29", "primary_isbn13": "9780143130604", "rank": 7}, {"display_name": "Espionage", "asterisk": 0, "ranks_last_week": null, "list_name": "Espionage", "weeks_on_list": 0, "published_date": "2016-10-09", "primary_isbn10": "1595231102", "dagger": 0, "bestsellers_date": "2016-09-24", "primary_isbn13": "9781595231109", "rank": 10}, {"display_name": "Espionage", "asterisk": 0, "ranks_last_week": null, "list_name": "Espionage", "weeks_on_list": 0, "published_date": "2016-09-11", "primary_isbn10": "073520943X", "dagger": 0, "bestsellers_date": "2016-08-27", "primary_isbn13": "9780735209435", "rank": 8}, {"display_name": "Espionage", "asterisk": 0, "ranks_last_week": null, "list_name": "Espionage", "weeks_on_list": 0, "published_date": "2016-08-14", "primary_isbn10": "073520943X", "dagger": 0, "bestsellers_date": "2016-07-30", "primary_isbn13": "9780735209435", "rank": 2}, {"display_name": "Combined Print & E-Book Nonfiction", "asterisk": 0, "ranks_last_week": null, "list_name": "Combined Print and E-Book Nonfiction", "weeks_on_list": 15, "published_date": "2016-07-10", "primary_isbn10": "", "dagger": 0, "bestsellers_date": "2016-06-25", "primary_isbn13": "9780698137653", "rank": 6}, {"display_name": "Politics and American History", "asterisk": 0, "ranks_last_week": null, "list_name": "Hardcover Political Books", "weeks_on_list": 0, "published_date": "2016-07-10", "primary_isbn10": "", "dagger": 0, "bestsellers_date": "2016-06-25", "primary_isbn13": "9780698137653", "rank": 8}, {"display_name": "Espionage", "asterisk": 0, "ranks_last_week": null, "list_name": "Espionage", "weeks_on_list": 0, "published_date": "2016-07-10", "primary_isbn10": "", "dagger": 0, "bestsellers_date": "2016-06-25", "primary_isbn13": "9780698137653", "rank": 1}, {"display_name": "E-Book Nonfiction", "asterisk": 0, "ranks_last_week": null, "list_name": "E-Book Nonfiction", "weeks_on_list": 17, "published_date": "2016-07-10", "primary_isbn10": "", "dagger": 0, "bestsellers_date": "2016-06-25", "primary_isbn13": "9780698137653", "rank": 1}, {"display_name": "Espionage", "asterisk": 0, "ranks_last_week": null, "list_name": "Espionage", "weeks_on_list": 0, "published_date": "2016-06-12", "primary_isbn10": "1595231102", "dagger": 0, "bestsellers_date": "2016-05-28", "primary_isbn13": "9781595231109", "rank": 4}, {"display_name": "Espionage", "asterisk": 0, "ranks_last_week": null, "list_name": "Espionage", "weeks_on_list": 0, "published_date": "2016-05-15", "primary_isbn10": "1595231102", "dagger": 0, "bestsellers_date": "2016-04-30", "primary_isbn13": "9781595231109", "rank": 5}, {"display_name": "Espionage", "asterisk": 0, "ranks_last_week": null, "list_name": "Espionage", "weeks_on_list": 0, "published_date": "2016-02-14", "primary_isbn10": "1595231102", "dagger": 0, "bestsellers_date": "2016-01-30", "primary_isbn13": "9781595231109", "rank": 6}, {"display_name": "Espionage", "asterisk": 0, "ranks_last_week": null, "list_name": "Espionage", "weeks_on_list": 0, "published_date": "2016-01-10", "primary_isbn10": "1595231102", "dagger": 0, "bestsellers_date": "2015-12-26", "primary_isbn13": "9781595231109", "rank": 3}, {"display_name": "Espionage", "asterisk": 0, "ranks_last_week": null, "list_name": "Espionage", "weeks_on_list": 0, "published_date": "2015-12-13", "primary_isbn10": "1595231102", "dagger": 0, "bestsellers_date": "2015-11-28", "primary_isbn13": "9781595231109", "rank": 9}, {"display_name": "Espionage", "asterisk": 0, "ranks_last_week": null, "list_name": "Espionage", "weeks_on_list": 0, "published_date": "2015-10-11", "primary_isbn10": "1595231102", "dagger": 0, "bestsellers_date": "2015-09-26", "primary_isbn13": "9781595231109", "rank": 9}, {"display_name": "Espionage", "asterisk": 0, "ranks_last_week": null, "list_name": "Espionage", "weeks_on_list": 0, "published_date": "2015-09-13", "primary_isbn10": "1595231102", "dagger": 0, "bestsellers_date": "2015-08-29", "primary_isbn13": "9781595231109", "rank": 6}, {"display_name": "Espionage", "asterisk": 0, "ranks_last_week": null, "list_name": "Espionage", "weeks_on_list": 0, "published_date": "2015-08-09", "primary_isbn10": "1595231102", "dagger": 0, "bestsellers_date": "2015-07-25", "primary_isbn13": "9781595231109", "rank": 7}, {"display_name": "Espionage", "asterisk": 0, "ranks_last_week": null, "list_name": "Espionage", "weeks_on_list": 0, "published_date": "2015-07-12", "primary_isbn10": "1595231102", "dagger": 0, "bestsellers_date": "2015-06-27", "primary_isbn13": "9781595231109", "rank": 5}], "price": 0, "contributor": "by Brian Kilmeade and Don Yaeger", "publisher": "Sentinel", "isbns": [{"isbn10": "159523103X", "isbn13": "9781595231031"}, {"isbn10": "1611762278", "isbn13": "9781611762273"}, {"isbn10": "1595231102", "isbn13": "9781595231109"}, {"isbn10": "073520943X", "isbn13": "9780735209435"}, {"isbn10": "0143130609", "isbn13": "9780143130604"}], "title": "GEORGE WASHINGTON'S SECRET SIX", "author": "Brian Kilmeade and Don Yaeger", "contributor_note": "", "age_group": "", "description": "The story of the Culper spy ring, which aided the American cause during the Revolution."}, {"reviews": [{"article_chapter_link": null, "book_review_link": "", "first_chapter_link": null, "sunday_review_link": "https://www.nytimes.com/2003/05/18/books/children-s-books-the-george-washington-bridge.html"}], "ranks_history": [], "price": 0, "contributor": null, "publisher": null, "isbns": [{"isbn10": "0312376049", "isbn13": "9780312376048"}], "title": "George Washington's Teeth", "author": "Madeleine Comora", "contributor_note": null, "age_group": null, "description": null}, {"reviews": [{"article_chapter_link": null, "book_review_link": "", "first_chapter_link": null, "sunday_review_link": "https://www.nytimes.com/1997/11/16/books/the-founding-of-a-father.html"}], "ranks_history": [], "price": 0, "contributor": null, "publisher": null, "isbns": [{"isbn10": "080505992X", "isbn13": "9780805059922"}], "title": "George Washington: A Life", "author": "Willard Sterne Randall", "contributor_note": null, "age_group": null, "description": null}, {"reviews": [{"article_chapter_link": "", "book_review_link": "https://www.nytimes.com/2010/03/24/books/24book.html", "first_chapter_link": "https://www.nytimes.com/2010/03/24/books/book-george-nicholas-and-wilhelm.html", "sunday_review_link": ""}], "ranks_history": [], "price": 0, "contributor": "by Miranda Carter", "publisher": "Knopf", "isbns": [{"isbn10": "1400043638", "isbn13": "9781400043637"}], "title": "GEORGE, NICHOLAS AND WILHELM", "author": "Miranda Carter", "contributor_note": "", "age_group": "", "description": ""}, {"reviews": [{"article_chapter_link": "", "book_review_link": "", "first_chapter_link": "", "sunday_review_link": ""}], "ranks_history": [], "price": 0, "contributor": "by Mark Childress", "publisher": "Little, Brown", "isbns": [{"isbn10": "0316033049", "isbn13": "9780316033046"}], "title": "GEORGIA BOTTOMS", "author": "Mark Childress", "contributor_note": "", "age_group": "", "description": ""}, {"reviews": [{"article_chapter_link": "", "book_review_link": "", "first_chapter_link": "", "sunday_review_link": ""}], "ranks_history": [], "price": 0, "contributor": "by Trisha Yearwood with Gwen Yearwood and Beth Yearwood Bernard", "publisher": "Clarkson Potter", "isbns": [], "title": "GEORGIA COOKING IN AN OKLAHOMA KITCHEN", "author": "Trisha Yearwood with Gwen Yearwood and Beth Yearwood Bernard", "contributor_note": "", "age_group": "", "description": ""}, {"reviews": [{"article_chapter_link": "", "book_review_link": "", "first_chapter_link": "", "sunday_review_link": ""}], "ranks_history": [{"display_name": "E-Book Nonfiction", "asterisk": 0, "ranks_last_week": null, "list_name": "E-Book Nonfiction", "weeks_on_list": 0, "published_date": "2016-07-10", "primary_isbn10": "1504025636", "dagger": 0, "bestsellers_date": "2016-06-25", "primary_isbn13": "9781504025638", "rank": 14}], "price": 0, "contributor": "by Roxana Robinson", "publisher": "Open Road Media", "isbns": [{"isbn10": "1504025636", "isbn13": "9781504025638"}], "title": "GEORGIA O'KEEFFE", "author": "Roxana Robinson", "contributor_note": "", "age_group": "", "description": ""}, {"reviews": [{"article_chapter_link": null, "book_review_link": "", "first_chapter_link": null, "sunday_review_link": "https://www.nytimes.com/1993/05/16/books/crazy-with-women-lucky-with-spain.html"}], "ranks_history": [], "price": 0, "contributor": null, "publisher": null, "isbns": [{"isbn10": "039303464X", "isbn13": "9780393034646"}], "title": "Gerald Brenan: The Interior Castle : A Biography", "author": "Jonathan Gathorne-Hardy", "contributor_note": null, "age_group": null, "description": null}, {"reviews": [{"article_chapter_link": null, "book_review_link": "", "first_chapter_link": null, "sunday_review_link": "https://www.nytimes.com/1985/12/29/books/death-as-a-parlor-game.html"}], "ranks_history": [], "price": 0, "contributor": null, "publisher": null, "isbns": [{"isbn10": "0671606557", "isbn13": "9780671606558"}], "title": "Gerald's Party (Coover, Robert)", "author": "Robert Coover", "contributor_note": null, "age_group": null, "description": null}, {"reviews": [{"article_chapter_link": null, "book_review_link": "", "first_chapter_link": null, "sunday_review_link": "https://www.nytimes.com/1999/05/09/books/back-to-the-barricades.html"}], "ranks_history": [], "price": 0, "contributor": null, "publisher": null, "isbns": [{"isbn10": "1860661750", "isbn13": "9781860661754"}], "title": "Germaine Greer: Untamed Shrew", "author": "Christine Wallace", "contributor_note": null, "age_group": null, "description": null}, {"reviews": [{"article_chapter_link": null, "book_review_link": "", "first_chapter_link": null, "sunday_review_link": "https://www.nytimes.com/1982/03/14/books/false-asylum.html"}], "ranks_history": [], "price": 0, "contributor": null, "publisher": null, "isbns": [{"isbn10": "080781492X", "isbn13": "9780807814925"}], "title": "German Writers in Soviet Exile, 1933-1945", "author": "David Pike", "contributor_note": null, "age_group": null, "description": null}, {"reviews": [{"article_chapter_link": null, "book_review_link": "", "first_chapter_link": null, "sunday_review_link": "https://www.nytimes.com/1996/03/31/books/together-again.html"}], "ranks_history": [], "price": 0, "contributor": null, "publisher": null, "isbns": [{"isbn10": "0674353250", "isbn13": "9780674353251"}], "title": "Germany Unified and Europe Transformed: A Study in Statecraft", "author": "Condoleezza Rice", "contributor_note": null, "age_group": null, "description": null}, {"reviews": [{"article_chapter_link": null, "book_review_link": "", "first_chapter_link": null, "sunday_review_link": "https://www.nytimes.com/2001/10/14/books/no-place-to-hide.html"}], "ranks_history": [], "price": 0, "contributor": null, "publisher": null, "isbns": [{"isbn10": "0684871599", "isbn13": "9780684871592"}], "title": "Germs: Biological Weapons and America's Secret War", "author": "Stephen Engelberg", "contributor_note": null, "age_group": null, "description": null}, {"reviews": [{"article_chapter_link": null, "book_review_link": "", "first_chapter_link": null, "sunday_review_link": "https://www.nytimes.com/1991/06/30/books/elgar-on-the-amazon.html"}], "ranks_history": [], "price": 0, "contributor": null, "publisher": null, "isbns": [{"isbn10": "0939149486", "isbn13": "9780939149483"}], "title": "Gerontius", "author": "James Hamilton-Paterson", "contributor_note": null, "age_group": null, "description": null}, {"reviews": [{"article_chapter_link": null, "book_review_link": "", "first_chapter_link": null, "sunday_review_link": "https://www.nytimes.com/2000/02/27/books/spoiled-rotten-in-denmark.html"}], "ranks_history": [], "price": 0, "contributor": null, "publisher": null, "isbns": [{"isbn10": "0449006972", "isbn13": "9780449006979"}], "title": "Gertrude and Claudius: A Novel", "author": "John Updike", "contributor_note": null, "age_group": null, "description": null}, {"reviews": [{"article_chapter_link": null, "book_review_link": "", "first_chapter_link": null, "sunday_review_link": "https://www.nytimes.com/2007/04/29/books/review/Worth.t.html"}], "ranks_history": [], "price": 0, "contributor": null, "publisher": null, "isbns": [{"isbn10": "0374531358", "isbn13": "9780374531355"}], "title": "Gertrude Bell: Queen of the Desert, Shaper of Nations", "author": "Georgina Howell", "contributor_note": null, "age_group": null, "description": null}, {"reviews": [{"article_chapter_link": null, "book_review_link": "", "first_chapter_link": null, "sunday_review_link": "https://www.nytimes.com/1998/08/30/books/the-sensuous-woman.html"}], "ranks_history": [], "price": 0, "contributor": null, "publisher": null, "isbns": [{"isbn10": "0688172261", "isbn13": "9780688172268"}], "title": "Gertrude of Stony Island Avenue (US)", "author": "James Purdy", "contributor_note": null, "age_group": null, "description": null}, {"reviews": [{"article_chapter_link": null, "book_review_link": "", "first_chapter_link": null, "sunday_review_link": "https://www.nytimes.com/2005/12/18/books/review/18harrison.html"}], "ranks_history": [], "price": 0, "contributor": null, "publisher": null, "isbns": [{"isbn10": "0143037927", "isbn13": "9780143037927"}], "title": "Get a Life", "author": "Nadine Gordimer", "contributor_note": null, "age_group": null, "description": null}, {"reviews": [{"article_chapter_link": "", "book_review_link": "", "first_chapter_link": "", "sunday_review_link": ""}], "ranks_history": [], "price": 16.99, "contributor": "by Darby Conley", "publisher": "Andrews McMeel Publishing", "isbns": [{"isbn10": "1449427987", "isbn13": "9781449427986"}], "title": "GET FUZZY: THE STINKING", "author": "Dar Conley", "contributor_note": "", "age_group": "", "description": "This comic strip chronicles the life of Rob Wilco (a nerdy vegan), Bucky (a mean cat) and Satchel (a perceptive dog)."}, {"reviews": [{"article_chapter_link": null, "book_review_link": "", "first_chapter_link": null, "sunday_review_link": "https://www.nytimes.com/2000/04/09/books/yellow-brick-road.html"}], "ranks_history": [], "price": 0, "contributor": null, "publisher": null, "isbns": [{"isbn10": "0385335156", "isbn13": "9780385335157"}], "title": "Get Happy: The Life of Judy Garland", "author": "Gerald Clarke", "contributor_note": null, "age_group": null, "description": null}]}