{"num_results": 30429, "status": "OK", "copyright": "Copyright (c) 2017 The New York Times Company.  All Rights Reserved.", "results": [{"reviews": [{"article_chapter_link": "", "book_review_link": "", "first_chapter_link": "", "sunday_review_link": ""}], "ranks_history": [{"display_name": "Crime and Punishment", "asterisk": 0, "ranks_last_week": null, "list_name": "Crime and Punishment", "weeks_on_list": 0, "published_date": "2014-11-09", "primary_isbn10": "0767915607", "dagger": 0, "bestsellers_date": "2014-10-25", "primary_isbn13": "9780767915601", "rank": 5}], "price": 0, "contributor": "by Frank W. Abagnale with Stan Redding", "publisher": "Broadway Books", "isbns": [{"isbn10": "0767915607", "isbn13": "9780767915601"}, {"isbn10": "0767905385", "isbn13": "9780767905381"}], "title": "CATCH ME IF YOU CAN", "author": "Frank W Abagnale with Stan Redding", "contributor_note": "", "age_group": "", "description": "The criminal career of the international con artist, imposter and forger."}, {"reviews": [{"article_chapter_link": "", "book_review_link": "", "first_chapter_link": "", "sunday_review_link": ""}], "ranks_history": [], "price": 0, "contributor": "by Kristan Higgins", "publisher": "Harlequin", "isbns": [{"isbn10": "1426861958", "isbn13": "9781426861956"}], "title": "CATCH OF THE DAY", "author": "Kristan Higgins", "contributor_note": "", "age_group": "", "description": ""}, {"reviews": [{"article_chapter_link": "", "book_review_link": "", "first_chapter_link": "", "sunday_review_link": "https://www.nytimes.com/2009/10/11/books/review/Zevin-t.html"}], "ranks_history": [], "price": 17.99, "contributor": "by Suzanne Collins", "publisher": "Scholastic", "isbns": [], "title": "CATCHING FIRE", "author": "Suzanne Collins", "contributor_note": "", "age_group": "Ages 12 and up", "description": "The protagonist of \"The Hunger Games\" returns."}, {"reviews": [{"article_chapter_link": "", "book_review_link": "", "first_chapter_link": "", "sunday_review_link": ""}], "ranks_history": [], "price": 0, "contributor": "by Sherryl Woods", "publisher": "Harlequin", "isbns": [{"isbn10": "077831359X", "isbn13": "9780778313595"}], "title": "CATCHING FIREFLIES", "author": "Sherryl Woods", "contributor_note": "", "age_group": "", "description": "The high school teacher Laura Reed and the pediatrician J.C. Fullerton fall in love while working together to stop bullying in Serenity, S.C.; a Sweet Magnolia novel."}, {"reviews": [{"article_chapter_link": null, "book_review_link": "", "first_chapter_link": null, "sunday_review_link": "https://www.nytimes.com/2000/09/10/books/books-in-brief-fiction-poetry-945382.html"}], "ranks_history": [], "price": 0, "contributor": null, "publisher": null, "isbns": [{"isbn10": "0345440005", "isbn13": "9780345440006"}], "title": "Catching Heaven (Ballantine Reader's Circle)", "author": "Sands Hall", "contributor_note": null, "age_group": null, "description": null}, {"reviews": [{"article_chapter_link": "", "book_review_link": "", "first_chapter_link": "", "sunday_review_link": ""}], "ranks_history": [], "price": 0, "contributor": "by Bill Evans and Marianna Jameson", "publisher": "Tor", "isbns": [], "title": "CATEGORY 7", "author": "Bill Evans and Marianna Jameson", "contributor_note": "", "age_group": "", "description": ""}, {"reviews": [{"article_chapter_link": "", "book_review_link": "", "first_chapter_link": "", "sunday_review_link": ""}], "ranks_history": [{"display_name": "Advice, How-To & Miscellaneous", "asterisk": 1, "ranks_last_week": null, "list_name": "Advice How-To and Miscellaneous", "weeks_on_list": 1, "published_date": "2013-11-03", "primary_isbn10": "0071821244", "dagger": 1, "bestsellers_date": "2013-10-19", "primary_isbn13": "9780071821247", "rank": 7}, {"display_name": "Business", "asterisk": 0, "ranks_last_week": null, "list_name": "Business Books", "weeks_on_list": 0, "published_date": "2013-11-03", "primary_isbn10": "0071821244", "dagger": 1, "bestsellers_date": "2013-10-26", "primary_isbn13": "9780071821247", "rank": 8}], "price": 0, "contributor": "by Craig T. Bouchard and James V. Koch", "publisher": "McGraw-Hill Education", "isbns": [{"isbn10": "0071821244", "isbn13": "9780071821247"}], "title": "CATERPILLAR WAY", "author": "Craig T Bouchard and James V Koch", "contributor_note": "", "age_group": "", "description": "A biography of Caterpillar Inc., as a tale of successful business management."}, {"reviews": [{"article_chapter_link": null, "book_review_link": "", "first_chapter_link": null, "sunday_review_link": "https://www.nytimes.com/1983/09/11/books/stories-of-our-loneliness.html"}], "ranks_history": [], "price": 0, "contributor": null, "publisher": null, "isbns": [{"isbn10": "0679723692", "isbn13": "9780679723691"}], "title": "Cathedral", "author": "Raymond Carver", "contributor_note": null, "age_group": null, "description": null}, {"reviews": [{"article_chapter_link": "", "book_review_link": "", "first_chapter_link": "", "sunday_review_link": "https://www.nytimes.com/2011/11/20/books/review/catherine-the-great-portrait-of-a-woman-by-robert-k-massie-book-review.html"}], "ranks_history": [{"display_name": "Paperback Nonfiction", "asterisk": 0, "ranks_last_week": null, "list_name": "Paperback Nonfiction", "weeks_on_list": 0, "published_date": "2013-02-17", "primary_isbn10": "0345408772", "dagger": 0, "bestsellers_date": "2013-02-02", "primary_isbn13": "9780345408778", "rank": 35}, {"display_name": "Paperback Nonfiction", "asterisk": 0, "ranks_last_week": null, "list_name": "Paperback Nonfiction", "weeks_on_list": 0, "published_date": "2013-02-10", "primary_isbn10": "0345408772", "dagger": 0, "bestsellers_date": "2013-01-26", "primary_isbn13": "9780345408778", "rank": 30}, {"display_name": "Paperback Nonfiction", "asterisk": 0, "ranks_last_week": null, "list_name": "Paperback Nonfiction", "weeks_on_list": 0, "published_date": "2013-02-03", "primary_isbn10": "0345408772", "dagger": 0, "bestsellers_date": "2013-01-19", "primary_isbn13": "9780345408778", "rank": 32}, {"display_name": "Paperback Nonfiction", "asterisk": 0, "ranks_last_week": null, "list_name": "Paperback Nonfiction", "weeks_on_list": 0, "published_date": "2013-01-27", "primary_isbn10": "0345408772", "dagger": 0, "bestsellers_date": "2013-01-12", "primary_isbn13": "9780345408778", "rank": 29}, {"display_name": "Paperback Nonfiction", "asterisk": 0, "ranks_last_week": null, "list_name": "Paperback Nonfiction", "weeks_on_list": 0, "published_date": "2013-01-20", "primary_isbn10": "0345408772", "dagger": 0, "bestsellers_date": "2013-01-05", "primary_isbn13": "9780345408778", "rank": 27}, {"display_name": "Paperback Nonfiction", "asterisk": 0, "ranks_last_week": null, "list_name": "Paperback Nonfiction", "weeks_on_list": 0, "published_date": "2013-01-13", "primary_isbn10": "0345408772", "dagger": 0, "bestsellers_date": "2012-12-29", "primary_isbn13": "9780345408778", "rank": 23}, {"display_name": "Paperback Nonfiction", "asterisk": 0, "ranks_last_week": null, "list_name": "Paperback Nonfiction", "weeks_on_list": 0, "published_date": "2013-01-06", "primary_isbn10": "0345408772", "dagger": 0, "bestsellers_date": "2012-12-22", "primary_isbn13": "9780345408778", "rank": 25}, {"display_name": "Paperback Nonfiction", "asterisk": 0, "ranks_last_week": null, "list_name": "Paperback Nonfiction", "weeks_on_list": 0, "published_date": "2012-12-30", "primary_isbn10": "0345408772", "dagger": 0, "bestsellers_date": "2012-12-15", "primary_isbn13": "9780345408778", "rank": 25}, {"display_name": "Paperback Nonfiction", "asterisk": 0, "ranks_last_week": null, "list_name": "Paperback Nonfiction", "weeks_on_list": 0, "published_date": "2012-12-23", "primary_isbn10": "0345408772", "dagger": 0, "bestsellers_date": "2012-12-08", "primary_isbn13": "9780345408778", "rank": 24}, {"display_name": "Paperback Nonfiction", "asterisk": 0, "ranks_last_week": null, "list_name": "Paperback Nonfiction", "weeks_on_list": 0, "published_date": "2012-12-16", "primary_isbn10": "0345408772", "dagger": 0, "bestsellers_date": "2012-12-01", "primary_isbn13": "9780345408778", "rank": 29}, {"display_name": "Paperback Nonfiction", "asterisk": 0, "ranks_last_week": null, "list_name": "Paperback Nonfiction", "weeks_on_list": 0, "published_date": "2012-12-09", "primary_isbn10": "0345408772", "dagger": 0, "bestsellers_date": "2012-11-24", "primary_isbn13": "9780345408778", "rank": 31}, {"display_name": "Paperback Nonfiction", "asterisk": 0, "ranks_last_week": null, "list_name": "Paperback Nonfiction", "weeks_on_list": 0, "published_date": "2012-12-02", "primary_isbn10": "0345408772", "dagger": 0, "bestsellers_date": "2012-11-17", "primary_isbn13": "9780345408778", "rank": 31}], "price": 0, "contributor": "by Robert K. Massie", "publisher": "Random House", "isbns": [{"isbn10": "0679456724", "isbn13": "9780679456728"}, {"isbn10": "158836044X", "isbn13": "9781588360441"}, {"isbn10": "0345408772", "isbn13": "9780345408778"}, {"isbn10": "1594136157", "isbn13": "9781594136153"}], "title": "CATHERINE THE GREAT", "author": "Robert K Massie", "contributor_note": "", "age_group": "", "description": "An 18th-century German princess who became Empress of All the Russias."}, {"reviews": [{"article_chapter_link": null, "book_review_link": "", "first_chapter_link": null, "sunday_review_link": "https://www.nytimes.com/1993/03/21/books/the-gospel-of-the-marketplace.html"}], "ranks_history": [], "price": 0, "contributor": null, "publisher": null, "isbns": [{"isbn10": "002923235X", "isbn13": "9780029232354"}], "title": "Catholic Ethic And The Spirit Of Capitalism", "author": "Michael Novak", "contributor_note": null, "age_group": null, "description": null}, {"reviews": [{"article_chapter_link": null, "book_review_link": "", "first_chapter_link": null, "sunday_review_link": "https://www.nytimes.com/2006/04/16/books/review/16allitt.html"}], "ranks_history": [], "price": 0, "contributor": null, "publisher": null, "isbns": [{"isbn10": "0465049362", "isbn13": "9780465049363"}], "title": "Catholic Matters: Confusion, Controversy, and the Splendor of Truth", "author": "Richard John Neuhaus", "contributor_note": null, "age_group": null, "description": null}, {"reviews": [{"article_chapter_link": "", "book_review_link": "", "first_chapter_link": "", "sunday_review_link": ""}], "ranks_history": [{"display_name": "Animals", "asterisk": 0, "ranks_last_week": null, "list_name": "Animals", "weeks_on_list": 0, "published_date": "2014-11-09", "primary_isbn10": "0399166017", "dagger": 0, "bestsellers_date": "2014-10-25", "primary_isbn13": "9780399166013", "rank": 1}, {"display_name": "Advice, How-To & Miscellaneous", "asterisk": 0, "ranks_last_week": null, "list_name": "Advice How-To and Miscellaneous", "weeks_on_list": 0, "published_date": "2014-11-02", "primary_isbn10": "0399166017", "dagger": 0, "bestsellers_date": "2014-10-18", "primary_isbn13": "9780399166013", "rank": 17}], "price": 0, "contributor": "by Jackson Galaxy and Kate Benjamin", "publisher": "Tarcher/Penguin", "isbns": [{"isbn10": "0399166017", "isbn13": "9780399166013"}, {"isbn10": "1101632313", "isbn13": "9781101632314"}], "title": "CATIFICATION", "author": "Jackson Galaxy and Kate Benjamin", "contributor_note": "", "age_group": "", "description": "Safe and stylish design ideas for living spaces that are shared by felines and humans."}, {"reviews": [{"article_chapter_link": "", "book_review_link": "", "first_chapter_link": "", "sunday_review_link": ""}], "ranks_history": [{"display_name": "Animals", "asterisk": 0, "ranks_last_week": null, "list_name": "Animals", "weeks_on_list": 0, "published_date": "2015-12-13", "primary_isbn10": "0399176993", "dagger": 0, "bestsellers_date": "2015-11-28", "primary_isbn13": "9780399176999", "rank": 2}], "price": 0, "contributor": "by Jackson Galaxy and Kate Benjamin", "publisher": "Tarcher Perigee", "isbns": [{"isbn10": "0399176993", "isbn13": "9780399176999"}], "title": "CATIFY TO SATISFY", "author": "Jackson Galaxy and Kate Benjamin", "contributor_note": "", "age_group": "", "description": "Home design strategies to address everyday cat care needs and issues."}, {"reviews": [{"article_chapter_link": null, "book_review_link": "", "first_chapter_link": null, "sunday_review_link": "https://www.nytimes.com/1998/05/31/books/improving-on-nature.html"}], "ranks_history": [], "price": 0, "contributor": null, "publisher": null, "isbns": [{"isbn10": "0393319903", "isbn13": "9780393319903"}], "title": "Cats' Paws and Catapults: Mechanical Worlds of Nature and People", "author": "Steven Vogel", "contributor_note": null, "age_group": null, "description": null}, {"reviews": [{"article_chapter_link": "", "book_review_link": "", "first_chapter_link": "", "sunday_review_link": ""}], "ranks_history": [{"display_name": "Paperback Graphic Books", "asterisk": 0, "ranks_last_week": null, "list_name": "Paperback Graphic Books", "weeks_on_list": 1, "published_date": "2013-03-24", "primary_isbn10": "1401238394", "dagger": 0, "bestsellers_date": "2013-03-09", "primary_isbn13": "9781401238391", "rank": 7}], "price": 14.99, "contributor": "by Judd Winick and Adriana Melo", "publisher": "DC Comics", "isbns": [{"isbn10": "1401238394", "isbn13": "9781401238391"}], "title": "CATWOMAN, VOL. 2", "author": "Judd Winick and Adriana Melo", "contributor_note": "", "age_group": "", "description": "Catwoman has a new buddy, Spark, and a new enemy, Dollhouse, who likes to kidnap children."}, {"reviews": [{"article_chapter_link": "", "book_review_link": "", "first_chapter_link": "", "sunday_review_link": ""}], "ranks_history": [], "price": 14.99, "contributor": "by Judd Winick and Guillem March", "publisher": "DC Comics", "isbns": [{"isbn10": "140123464X", "isbn13": "9781401234645"}], "title": "CATWOMAN: THE GAME", "author": "Judd Winick and Guillem March", "contributor_note": "", "age_group": "", "description": "Has Catwoman stolen from the wrong man?"}, {"reviews": [{"article_chapter_link": "", "book_review_link": "", "first_chapter_link": "", "sunday_review_link": ""}], "ranks_history": [], "price": 0, "contributor": "by Harlan Coben", "publisher": "Signet", "isbns": [{"isbn10": "052595158X", "isbn13": "9780525951582"}, {"isbn10": "0451232704", "isbn13": "9780451232700"}], "title": "CAUGHT", "author": "Harlan Coben", "contributor_note": "", "age_group": "", "description": "A social worker walks into the trap of a reporter who has made a name for herself bringing down sex offenders."}, {"reviews": [{"article_chapter_link": null, "book_review_link": "", "first_chapter_link": null, "sunday_review_link": "https://www.nytimes.com/1985/12/01/books/up-above-brooklyn.html"}], "ranks_history": [], "price": 0, "contributor": null, "publisher": null, "isbns": [{"isbn10": "0345339193", "isbn13": "9780345339195"}], "title": "Caught", "author": "Jane Schwartz", "contributor_note": null, "age_group": null, "description": null}, {"reviews": [{"article_chapter_link": "", "book_review_link": "", "first_chapter_link": "", "sunday_review_link": ""}], "ranks_history": [{"display_name": "E-Book Fiction", "asterisk": 0, "ranks_last_week": null, "list_name": "E-Book Fiction", "weeks_on_list": 0, "published_date": "2013-02-24", "primary_isbn10": "None", "dagger": 0, "bestsellers_date": "2013-02-09", "primary_isbn13": "2940016017433", "rank": 28}], "price": 0, "contributor": "by Lauren Blakely", "publisher": "Lauren Blakely Books", "isbns": [], "title": "CAUGHT UP IN US", "author": "Lauren Blakely", "contributor_note": "", "age_group": "", "description": ""}, {"reviews": [{"article_chapter_link": "", "book_review_link": "", "first_chapter_link": "", "sunday_review_link": ""}], "ranks_history": [], "price": 0, "contributor": "by Lori Foster", "publisher": "HQN", "isbns": [], "title": "CAUGHT!", "author": "Lori Foster", "contributor_note": "", "age_group": "", "description": ""}]}