{"num_results": 30429, "status": "OK", "copyright": "Copyright (c) 2017 The New York Times Company.  All Rights Reserved.", "results": [{"reviews": [{"article_chapter_link": "", "book_review_link": "", "first_chapter_link": "", "sunday_review_link": ""}], "ranks_history": [], "price": 10.99, "contributor": "by Hiro Mashima", "publisher": "Kodansha Comics", "isbns": [{"isbn10": "1612622836", "isbn13": "9781612622835"}], "title": "FAIRY TAIL, VOL. 12", "author": "Hiro Mashima", "contributor_note": "", "age_group": "", "description": "The Fairy Tail are a group of powerful wizards."}, {"reviews": [{"article_chapter_link": "", "book_review_link": "", "first_chapter_link": "", "sunday_review_link": ""}], "ranks_history": [], "price": 10.99, "contributor": "by Hiro Mashima", "publisher": "Kodansha Comics", "isbns": [{"isbn10": "1935429329", "isbn13": "9781935429326"}], "title": "FAIRY TAIL, VOL. 13", "author": "Hiro Mashima", "contributor_note": "", "age_group": "", "description": "The Fairy Tail are a group of powerful wizards. In this volume, a civil war brews."}, {"reviews": [{"article_chapter_link": "", "book_review_link": "", "first_chapter_link": "", "sunday_review_link": ""}], "ranks_history": [], "price": 10.99, "contributor": "by Hiro Mashima", "publisher": "Kodansha Comics", "isbns": [{"isbn10": "1935429345", "isbn13": "9781935429340"}], "title": "FAIRY TAIL, VOL. 15", "author": "Hiro Mashima", "contributor_note": "", "age_group": "", "description": "The Fairy Tail is a club of powerful wizards."}, {"reviews": [{"article_chapter_link": "", "book_review_link": "", "first_chapter_link": "", "sunday_review_link": ""}], "ranks_history": [], "price": 10.99, "contributor": "by Hiro Mashima", "publisher": "Kodansha Comics", "isbns": [{"isbn10": "1935429353", "isbn13": "9781935429357"}], "title": "FAIRY TAIL, VOL. 16", "author": "Hiro Mashima", "contributor_note": "", "age_group": "", "description": "The Fairy Tail is a club of powerful wizards."}, {"reviews": [{"article_chapter_link": "", "book_review_link": "", "first_chapter_link": "", "sunday_review_link": ""}], "ranks_history": [], "price": 10.99, "contributor": "by Hiro Mashima", "publisher": "Kodansha Comics", "isbns": [{"isbn10": "161262054X", "isbn13": "9781612620541"}], "title": "FAIRY TAIL, VOL. 17", "author": "Hiro Mashima", "contributor_note": "", "age_group": "", "description": "The Fairy Tail are a group of powerful wizards. In this volume, the destructive spell, Nirvana, which has the power to change the good and evil emotions within people, is unleashed."}, {"reviews": [{"article_chapter_link": "", "book_review_link": "", "first_chapter_link": "", "sunday_review_link": ""}], "ranks_history": [], "price": 10.99, "contributor": "by Hiro Mashima", "publisher": "Kodansha Comics", "isbns": [{"isbn10": "1612620558", "isbn13": "9781612620558"}], "title": "FAIRY TAIL, VOL. 18", "author": "Hiro Mashima", "contributor_note": "", "age_group": "", "description": "The Fairy Tail are a group of powerful wizards."}, {"reviews": [{"article_chapter_link": "", "book_review_link": "", "first_chapter_link": "", "sunday_review_link": ""}], "ranks_history": [], "price": 10.99, "contributor": "by Hiro Mashima", "publisher": "Kodansha Comics", "isbns": [{"isbn10": "1612620566", "isbn13": "9781612620565"}], "title": "FAIRY TAIL, VOL. 19", "author": "Hiro Mashima", "contributor_note": "", "age_group": "", "description": "The Fairy Tail are a group of powerful wizards."}, {"reviews": [{"article_chapter_link": "", "book_review_link": "", "first_chapter_link": "", "sunday_review_link": ""}], "ranks_history": [], "price": 10.99, "contributor": "by Hiro Mashima", "publisher": "Kodansha Comics", "isbns": [{"isbn10": "1612620574", "isbn13": "9781612620572"}], "title": "FAIRY TAIL, VOL. 20", "author": "Hiro Mashima", "contributor_note": "", "age_group": "", "description": "The Fairy Tail are a group of powerful wizards."}, {"reviews": [{"article_chapter_link": "", "book_review_link": "", "first_chapter_link": "", "sunday_review_link": ""}], "ranks_history": [], "price": 10.99, "contributor": "by Hiro Mashima", "publisher": "Kodansha Comics", "isbns": [{"isbn10": "1612620604", "isbn13": "9781612620602"}], "title": "FAIRY TAIL, VOL. 23", "author": "Hiro Mashima", "contributor_note": "", "age_group": "", "description": "The Fairy Tail are a group of powerful wizards."}, {"reviews": [{"article_chapter_link": "", "book_review_link": "", "first_chapter_link": "", "sunday_review_link": ""}], "ranks_history": [], "price": 10.99, "contributor": "by Hiro Mashima", "publisher": "Kodansha Comics", "isbns": [{"isbn10": "1612622666", "isbn13": "9781612622668"}], "title": "FAIRY TAIL, VOL. 24", "author": "Hiro Mashima", "contributor_note": "", "age_group": "", "description": "The Fairy Tail are a group of powerful wizards."}, {"reviews": [{"article_chapter_link": "", "book_review_link": "", "first_chapter_link": "", "sunday_review_link": ""}], "ranks_history": [{"display_name": "Manga", "asterisk": 0, "ranks_last_week": null, "list_name": "Manga", "weeks_on_list": 2, "published_date": "2013-05-26", "primary_isbn10": "1612622674", "dagger": 0, "bestsellers_date": "2013-05-11", "primary_isbn13": "9781612622675", "rank": 10}, {"display_name": "Manga", "asterisk": 0, "ranks_last_week": null, "list_name": "Manga", "weeks_on_list": 1, "published_date": "2013-05-19", "primary_isbn10": "1612622674", "dagger": 0, "bestsellers_date": "2013-05-04", "primary_isbn13": "9781612622675", "rank": 2}], "price": 0, "contributor": "by Hiro Mashima", "publisher": "Kodansha Comics", "isbns": [{"isbn10": "1612622674", "isbn13": "9781612622675"}], "title": "FAIRY TAIL, VOL. 25", "author": "Hiro Mashima", "contributor_note": "", "age_group": "", "description": "The Fairy Tail are a group of powerful wizards."}, {"reviews": [{"article_chapter_link": "", "book_review_link": "", "first_chapter_link": "", "sunday_review_link": ""}], "ranks_history": [{"display_name": "Manga", "asterisk": 0, "ranks_last_week": null, "list_name": "Manga", "weeks_on_list": 1, "published_date": "2013-06-30", "primary_isbn10": "1612622682", "dagger": 0, "bestsellers_date": "2013-06-15", "primary_isbn13": "9781612622682", "rank": 2}], "price": 0, "contributor": "by Hiro Mashima", "publisher": "Kodansha Comics", "isbns": [{"isbn10": "1612622682", "isbn13": "9781612622682"}], "title": "FAIRY TAIL, VOL. 26", "author": "Hiro Mashima", "contributor_note": "", "age_group": "", "description": "The Fairy Tail are a group of powerful wizards."}, {"reviews": [{"article_chapter_link": "", "book_review_link": "", "first_chapter_link": "", "sunday_review_link": ""}], "ranks_history": [{"display_name": "Manga", "asterisk": 0, "ranks_last_week": null, "list_name": "Manga", "weeks_on_list": 2, "published_date": "2013-07-28", "primary_isbn10": "1612622690", "dagger": 0, "bestsellers_date": "2013-07-13", "primary_isbn13": "9781612622699", "rank": 7}, {"display_name": "Manga", "asterisk": 0, "ranks_last_week": null, "list_name": "Manga", "weeks_on_list": 1, "published_date": "2013-07-21", "primary_isbn10": "1612622690", "dagger": 0, "bestsellers_date": "2013-07-06", "primary_isbn13": "9781612622699", "rank": 4}], "price": 0, "contributor": "by Hiro Mashima", "publisher": "Kodansha Comics", "isbns": [{"isbn10": "1612622690", "isbn13": "9781612622699"}], "title": "FAIRY TAIL, VOL. 27", "author": "Hiro Mashima", "contributor_note": "", "age_group": "", "description": "The Fairy Tail are a group of powerful wizards."}, {"reviews": [{"article_chapter_link": "", "book_review_link": "", "first_chapter_link": "", "sunday_review_link": ""}], "ranks_history": [{"display_name": "Manga", "asterisk": 0, "ranks_last_week": null, "list_name": "Manga", "weeks_on_list": 1, "published_date": "2013-08-25", "primary_isbn10": "1612622704", "dagger": 0, "bestsellers_date": "2013-08-10", "primary_isbn13": "9781612622705", "rank": 3}], "price": 0, "contributor": "by Hiro Mashima", "publisher": "Kodansha Comics", "isbns": [{"isbn10": "1612622704", "isbn13": "9781612622705"}], "title": "FAIRY TAIL, VOL. 28", "author": "Hiro Mashima", "contributor_note": "", "age_group": "", "description": "The Fairy Tail are a group of powerful wizards."}, {"reviews": [{"article_chapter_link": "", "book_review_link": "", "first_chapter_link": "", "sunday_review_link": ""}], "ranks_history": [{"display_name": "Manga", "asterisk": 0, "ranks_last_week": null, "list_name": "Manga", "weeks_on_list": 2, "published_date": "2014-01-12", "primary_isbn10": "1612624103", "dagger": 0, "bestsellers_date": "2013-12-28", "primary_isbn13": "9781612624105", "rank": 8}, {"display_name": "Manga", "asterisk": 0, "ranks_last_week": null, "list_name": "Manga", "weeks_on_list": 1, "published_date": "2014-01-05", "primary_isbn10": "1612624103", "dagger": 0, "bestsellers_date": "2013-12-21", "primary_isbn13": "9781612624105", "rank": 4}], "price": 0, "contributor": "by Hiro Mashima", "publisher": "Kodansha Comics", "isbns": [{"isbn10": "1612624103", "isbn13": "9781612624105"}], "title": "FAIRY TAIL, VOL. 33", "author": "Hiro Mashima", "contributor_note": "", "age_group": "", "description": "The Grand Magic Games continue in this volume as Elfman prepares to face Bacchus."}, {"reviews": [{"article_chapter_link": "", "book_review_link": "", "first_chapter_link": "", "sunday_review_link": ""}], "ranks_history": [{"display_name": "Manga", "asterisk": 0, "ranks_last_week": null, "list_name": "Manga", "weeks_on_list": 1, "published_date": "2014-02-09", "primary_isbn10": "1612624111", "dagger": 0, "bestsellers_date": "2014-01-25", "primary_isbn13": "9781612624112", "rank": 7}], "price": 0, "contributor": "by Hiro Mashima", "publisher": "Kodansha Comics", "isbns": [{"isbn10": "1612624111", "isbn13": "9781612624112"}], "title": "FAIRY TAIL, VOL. 34", "author": "Hiro Mashima", "contributor_note": "", "age_group": "", "description": "At the Grand Magic Games, Ezra boldly claims that she will fight 100 monsters at once to reclaim Fairy Tail's honor."}, {"reviews": [{"article_chapter_link": "", "book_review_link": "", "first_chapter_link": "", "sunday_review_link": ""}], "ranks_history": [{"display_name": "Manga", "asterisk": 0, "ranks_last_week": null, "list_name": "Manga", "weeks_on_list": 2, "published_date": "2014-03-30", "primary_isbn10": "161262412X", "dagger": 0, "bestsellers_date": "2014-03-15", "primary_isbn13": "9781612624129", "rank": 8}, {"display_name": "Manga", "asterisk": 0, "ranks_last_week": null, "list_name": "Manga", "weeks_on_list": 1, "published_date": "2014-03-23", "primary_isbn10": "161262412X", "dagger": 0, "bestsellers_date": "2014-03-08", "primary_isbn13": "9781612624129", "rank": 9}], "price": 0, "contributor": "by Hiro Mashima", "publisher": "Kodansha Comics", "isbns": [{"isbn10": "161262412X", "isbn13": "9781612624129"}], "title": "FAIRY TAIL, VOL. 35", "author": "Hiro Mashima", "contributor_note": "", "age_group": "", "description": "Dragon slayers wage a fierce battle during the fourth day of the Grand Magic Games."}, {"reviews": [{"article_chapter_link": "", "book_review_link": "", "first_chapter_link": "", "sunday_review_link": ""}], "ranks_history": [{"display_name": "Manga", "asterisk": 0, "ranks_last_week": null, "list_name": "Manga", "weeks_on_list": 3, "published_date": "2014-04-27", "primary_isbn10": "1612624324", "dagger": 0, "bestsellers_date": "2014-04-12", "primary_isbn13": "9781612624327", "rank": 9}, {"display_name": "Manga", "asterisk": 0, "ranks_last_week": null, "list_name": "Manga", "weeks_on_list": 2, "published_date": "2014-04-20", "primary_isbn10": "1612624324", "dagger": 0, "bestsellers_date": "2014-04-05", "primary_isbn13": "9781612624327", "rank": 7}, {"display_name": "Manga", "asterisk": 0, "ranks_last_week": null, "list_name": "Manga", "weeks_on_list": 1, "published_date": "2014-04-13", "primary_isbn10": "1612624324", "dagger": 0, "bestsellers_date": "2014-03-29", "primary_isbn13": "9781612624327", "rank": 9}], "price": 0, "contributor": "by Hiro Mashima", "publisher": "Kodansha Comics", "isbns": [{"isbn10": "1612624324", "isbn13": "9781612624327"}], "title": "FAIRY TAIL, VOL. 36", "author": "Hiro Mashima", "contributor_note": "", "age_group": "", "description": "Fairy Tail vaults to the top of the rankings in the Grand Magic Games but why aren\u2019t they excited about their victory?"}, {"reviews": [{"article_chapter_link": "", "book_review_link": "", "first_chapter_link": "", "sunday_review_link": ""}], "ranks_history": [{"display_name": "Manga", "asterisk": 0, "ranks_last_week": null, "list_name": "Manga", "weeks_on_list": 3, "published_date": "2014-05-18", "primary_isbn10": "1612624332", "dagger": 0, "bestsellers_date": "2014-05-03", "primary_isbn13": "9781612624334", "rank": 5}, {"display_name": "Manga", "asterisk": 0, "ranks_last_week": null, "list_name": "Manga", "weeks_on_list": 2, "published_date": "2014-05-11", "primary_isbn10": "1612624332", "dagger": 0, "bestsellers_date": "2014-04-26", "primary_isbn13": "9781612624334", "rank": 6}, {"display_name": "Manga", "asterisk": 0, "ranks_last_week": null, "list_name": "Manga", "weeks_on_list": 1, "published_date": "2014-05-04", "primary_isbn10": "1612624332", "dagger": 0, "bestsellers_date": "2014-04-19", "primary_isbn13": "9781612624334", "rank": 2}], "price": 0, "contributor": "by Hiro Mashima", "publisher": "Kodansha Comics", "isbns": [{"isbn10": "1612624332", "isbn13": "9781612624334"}], "title": "FAIRY TAIL, VOL. 37", "author": "Hiro Mashima", "contributor_note": "", "age_group": "", "description": "Ezra faces not one but two of the most powerful female wizards in the world while Natsu barrels ahead with his reckless plan to rescue Lucy."}, {"reviews": [{"article_chapter_link": "", "book_review_link": "", "first_chapter_link": "", "sunday_review_link": ""}], "ranks_history": [{"display_name": "Manga", "asterisk": 0, "ranks_last_week": null, "list_name": "Manga", "weeks_on_list": 3, "published_date": "2014-06-15", "primary_isbn10": "1612624340", "dagger": 0, "bestsellers_date": "2014-05-31", "primary_isbn13": "9781612624341", "rank": 10}, {"display_name": "Manga", "asterisk": 0, "ranks_last_week": null, "list_name": "Manga", "weeks_on_list": 2, "published_date": "2014-06-08", "primary_isbn10": "1612624340", "dagger": 0, "bestsellers_date": "2014-05-24", "primary_isbn13": "9781612624341", "rank": 4}, {"display_name": "Manga", "asterisk": 0, "ranks_last_week": null, "list_name": "Manga", "weeks_on_list": 1, "published_date": "2014-06-01", "primary_isbn10": "1612624340", "dagger": 0, "bestsellers_date": "2014-05-17", "primary_isbn13": "9781612624341", "rank": 2}], "price": 0, "contributor": "by Hiro Mashima", "publisher": "Kodansha Comics", "isbns": [{"isbn10": "1612624340", "isbn13": "9781612624341"}], "title": "FAIRY TAIL, VOL. 38", "author": "Hiro Mashima", "contributor_note": "", "age_group": "", "description": "Erza, Gajeel and Laxus reach the finals of The Grand Magic Games but those events pale in comparison to another shocking development: the return of the dragons."}]}